emmett_prometheus/__init__.py
emmett_prometheus/__version__.py
emmett_prometheus/_imports.py
emmett_prometheus/ext.py
emmett_prometheus-0.2.0.dist-info/METADATA
emmett_prometheus-0.2.0.dist-info/WHEEL
emmett_prometheus-0.2.0.dist-info/licenses/LICENSE
emmett_prometheus-0.2.0.dist-info/RECORD
