Metadata-Version: 2.3
Name: emmett-prometheus
Version: 0.2.0
Summary: Prometheus extension for Emmett framework
Project-URL: Homepage, https://github.com/emmett-framework/prometheus
Project-URL: Funding, https://github.com/sponsors/gi0baro
Project-URL: Source, https://github.com/emmett-framework/prometheus
Project-URL: Issues, https://github.com/emmett-framework/prometheus/issues
Author-email: Giovanni Barillari <g@baro.dev>
License-Expression: BSD-3-Clause
License-File: LICENSE
Keywords: emmett,monitoring,prometheus
Classifier: Development Status :: 5 - Production/Stable
Classifier: Environment :: Web Environment
Classifier: Framework :: AsyncIO
Classifier: Intended Audience :: Developers
Classifier: License :: OSI Approved :: BSD License
Classifier: Operating System :: OS Independent
Classifier: Programming Language :: Python :: 3
Classifier: Programming Language :: Python :: 3.8
Classifier: Programming Language :: Python :: 3.9
Classifier: Programming Language :: Python :: 3.10
Classifier: Programming Language :: Python :: 3.11
Classifier: Programming Language :: Python :: 3.12
Classifier: Programming Language :: Python :: 3.13
Classifier: Topic :: Internet :: WWW/HTTP :: Dynamic Content
Classifier: Topic :: Software Development :: Libraries :: Python Modules
Classifier: Topic :: System :: Monitoring
Requires-Python: >=3.8
Requires-Dist: emmett-core~=1.0
Requires-Dist: prometheus-client~=0.21
